mqtt_client/entity.py
mqtt_client/main.py
mqtt_client/messaging.py
mqtt_client/payload.py
rest_client/__init__.py
rest_client/client.py
rest_client/errors.py
rest_client/py.typed
rest_client/types.py
exampleserverrepository-1.0.12.dist-info/METADATA
exampleserverrepository-1.0.12.dist-info/WHEEL
exampleserverrepository-1.0.12.dist-info/top_level.txt
exampleserverrepository-1.0.12.dist-info/RECORD
