Metadata-Version: 2.4
Name: exampleserverrepository
Version: 1.0.12
Summary: Generated REST & MQTT clients
Requires-Python: >=3.9
Requires-Dist: httpx<0.29.0,>=0.23.0
Requires-Dist: attrs>=22.2.0
Requires-Dist: paho-mqtt>=1.6.0
